setup.py
collective/__init__.py
collective.lead.egg-info/PKG-INFO
collective.lead.egg-info/SOURCES.txt
collective.lead.egg-info/dependency_links.txt
collective.lead.egg-info/entry_points.txt
collective.lead.egg-info/namespace_packages.txt
collective.lead.egg-info/not-zip-safe
collective.lead.egg-info/requires.txt
collective.lead.egg-info/top_level.txt
collective/lead/README.txt
collective/lead/__init__.py
collective/lead/configure.zcml
collective/lead/database.py
collective/lead/interfaces.py
collective/lead/tests.py
collective/lead/tx.py
docs/HISTORY.txt
docs/LICENSE.GPL
docs/LICENSE.txt