Metadata-Version: 1.0
Name: collective.lead
Version: 1.0
Summary: SQLAlchemy/Zope2 transaction integration
Home-page: http://svn.plone.org/svn/collective/collective.lead
Author: Martin Aspeli
Author-email: optilude@gmx.net
License: LGPL
Platform: UNKNOWN
Classifier: Framework :: Zope2
Classifier: Framework :: Zope3
Classifier: Programming Language :: Python
Classifier: Topic :: Software Development :: Libraries :: Python Modules
